datazip_sqloxide-0.1.26.dist-info/RECORD
datazip_sqloxide-0.1.26.dist-info/METADATA
datazip_sqloxide-0.1.26.dist-info/top_level.txt
datazip_sqloxide-0.1.26.dist-info/LICENSE
datazip_sqloxide-0.1.26.dist-info/WHEEL
sqloxide/sqloxide.cpython-37m-aarch64-linux-gnu.so
sqloxide/__init__.py
